rycronofy/__init__.py
rycronofy/rycronofy.py
rycronofy-0.4.dist-info/METADATA
rycronofy-0.4.dist-info/WHEEL
rycronofy-0.4.dist-info/top_level.txt
rycronofy-0.4.dist-info/RECORD
