Metadata-Version: 2.1
Name: rycronofy
Version: 0.4
Summary: A basic Python wrapper over the Cronofy calendar scheduling library
Home-page: UNKNOWN
Author: Ryan Mohta
Author-email: ryanmohta@gmail.com
License: UNKNOWN
Keywords: python,cronofy
Platform: UNKNOWN
Requires-Dist: requests
